{"program":"UAE (Dubai / Abu Dhabi)","fetchedAt":"2026-07-07T16:02:08.325Z","coord":{"lat":25.2048,"lon":55.2708,"radiusKm":60},"places":[{"id":364,"lat":25.0675924,"lon":55.1308557,"icon":"hotel","name":"Elementi Zen Marina","address":"Marina دبي","created_at":"2022-10-08T15:43:11Z","updated_at":"2025-09-18T05:36:33.33Z","verified_at":"2024-05-25T00:00:00Z","osm_id":"node:10084543967","phone":"+38167105622","description":"Amazing 2 br apartment with sea view available for rent. It is located on higher floor and is rented with no furniture for 1 year contract. For more location contact"},{"id":502,"lat":25.102757,"lon":55.1641325,"icon":"restaurant","name":"Chuno Deli","address":"Choueiri Building, Knowledge Village, Dubai Media City Dubai","opening_hours":"Su-Th 08:00-19:00","created_at":"2022-10-16T04:31:43Z","updated_at":"2025-09-18T05:36:33.049Z","verified_at":"2022-10-16T00:00:00Z","osm_id":"node:10105172657","phone":"+971 4 456 1232"},{"id":779,"lat":25.077795,"lon":55.1408377,"icon":"directions_car","name":"Elite Rentals","created_at":"2022-10-26T19:01:31Z","updated_at":"2025-09-18T05:36:30.603Z","verified_at":"2022-10-26T00:00:00Z","osm_id":"node:10130948506","phone":"+971585773249","website":"https://dubaiyachtbooking.com/"},{"id":2086,"lat":24.9818046,"lon":55.1756541,"icon":"bakery_dining","name":"La Boulangerie by Vulpes","address":"Dubai","opening_hours":"24/7","created_at":"2022-12-01T11:41:37Z","updated_at":"2026-06-30T04:13:40.096Z","verified_at":"2026-06-30T00:00:00Z","osm_id":"node:10230645967","phone":"+971 56 248 2253"},{"id":11579,"lat":25.1029978,"lon":55.1766588,"icon":"directions_car","name":"Yeti Car Rental","address":"1708 Al Ameri Tower, Barsha Heights Dubai 7819","opening_hours":"Mo-Fr 09:00-20:00; Sa,Su 10:00-20:00","created_at":"2022-09-25T08:45:08Z","updated_at":"2026-04-27T00:05:07.522Z","verified_at":"2025-04-27T00:00:00Z","osm_id":"node:4314158290","phone":"+971 55 184 8500","website":"https://yetiuae.com","email":"rent@yetiuae.com"},{"id":11977,"lat":25.1279838,"lon":55.2125014,"icon":"directions_car","name":"Andaleeb Cars","address":"Street 4 - Sheikh Zayed Road Al Quoz, Dubai","opening_hours":"Mo-Su 10:00-21:00","created_at":"2022-10-25T18:31:29Z","updated_at":"2026-04-27T00:05:07.523Z","verified_at":"2025-04-27T00:00:00Z","osm_id":"node:4902755391","phone":"+971 4 399 9015","website":"https://andaleebcars.com","email":"info@andaleebcars.com"},{"id":20917,"lat":25.0772149,"lon":55.1503414,"icon":"attach_money","name":"Nephos Global","address":"Oaks Liwa Heights Jumeirah Lakes Towers Dubai","created_at":"2024-10-02T11:24:21.874Z","updated_at":"2025-10-01T00:05:35.511Z","verified_at":"2024-10-01T00:00:00Z","osm_id":"node:12215717331","phone":"+971554118430"},{"id":21019,"lat":25.1732411,"lon":55.3023012,"icon":"hotel","name":"Amantius Apartments","address":"17 Riviera Dubai 58F2+7W","opening_hours":"Mo-Su 09:00-19:00","created_at":"2024-10-11T13:54:19.752Z","updated_at":"2025-09-18T05:36:33.049Z","verified_at":"2024-03-04T00:00:00Z","osm_id":"node:12244223301","phone":"+971 50 975 8540","website":"https://amantius.io/en","facebook":"https://www.facebook.com/amantius.apartments","instagram":"https://www.instagram.com/amantius.apartments/","email":"apartments@amantius.io"},{"id":29023,"lat":25.1145511,"lon":55.2052267,"icon":"home","name":"Tekce Real Estate","address":"9 شارع السيداف 1 دبي 00000","opening_hours":"Mo-Fr 09:00-18:00; Sa 10:00-15:00","created_at":"2025-10-01T19:32:39.175Z","updated_at":"2026-07-04T00:05:06.316Z","verified_at":"2025-10-01T00:00:00Z","osm_id":"node:11906886845","phone":"+971 521 958 490","website":"https://tekce.com/property-uae/dubai","twitter":"https://x.com/tekce_com/","facebook":"https://www.facebook.com/tekcecom/","instagram":"https://www.instagram.com/tekcecom/","email":"info@tekce.com"},{"id":33794,"lat":25.118636,"lon":55.3782183,"icon":"business","name":"Agence Welcome To Dubai","address":"A3 66 Street Dubai","opening_hours":"Mo-Su 09:00-21:00","created_at":"2026-01-15T03:43:07.096Z","updated_at":"2026-01-15T03:43:07.098Z","verified_at":"2026-01-15T00:00:00Z","osm_id":"node:13457218875","phone":"+971 585 660672","website":"https://welcometodubai.fr/","email":"agence.welcometodubai@gmail.com"},{"id":35526,"lat":25.077911,"lon":55.1530214,"icon":"diamond","name":"Studio ALOI","address":"Swiss Tower, 10th Floor, Cluster Y Dubai","opening_hours":"PH Mo-Fr 09:00-18:00 \"by appointment\"","created_at":"2026-02-25T23:04:48.93Z","updated_at":"2026-02-25T23:04:48.937Z","verified_at":"2026-02-25T00:00:00Z","osm_id":"node:13599623713","phone":"+971 4 279 8350","website":"https://www.studioaloi.com/","email":"info@myaloi.com"}],"areas":[{"id":234,"name":"Dubai Citadel","type":"community","url_alias":"dubai-citadel","icon":"https://static.btcmap.org/images/communities/dubai-citadel.jpg","website_url":"https://btcmap.org/community/dubai-citadel"},{"id":8,"name":"United Arab Emirates","type":"country","url_alias":"ae","icon":"https://static.btcmap.org/images/areas/8.png","website_url":"https://btcmap.org/country/ae"}]}